py_data_validator/__init__.py
py_data_validator/base_validator.py
py_data_validator/libs/__init__.py
py_data_validator/libs/helpers.py
py_data_validator/libs/rule_creator.py
py_data_validator/libs/rule_template.txt
py_data_validator/quick_validate.py
py_data_validator/rule.py
py_data_validator/rules/__init__.py
py_data_validator/rules/accepted.py
py_data_validator/rules/between.py
py_data_validator/rules/email.py
py_data_validator/rules/gt.py
py_data_validator/rules/gte.py
py_data_validator/rules/lt.py
py_data_validator/rules/lte.py
py_data_validator/rules/max.py
py_data_validator/rules/min.py
py_data_validator/rules/nullable.py
py_data_validator/rules/numeric.py
py_data_validator/rules/required.py
py_data_validator/rules/required_if.py
py_data_validator/rules/size.py
py_data_validator/rules/string.py
py_data_validator/rules_mapper.py
py_data_validator/validation_response.py
py_data_validator/validator.py
py_data_validator-0.1.4.dist-info/LICENSE.md
py_data_validator-0.1.4.dist-info/METADATA
py_data_validator-0.1.4.dist-info/WHEEL
py_data_validator-0.1.4.dist-info/RECORD
