Metadata-Version: 2.1
Name: py-data-validator
Version: 0.1.4
Summary: Python data validation library
License: MIT
Author: Krunal Dodiya
Author-email: kunal.dodiya1@gmail.com
Requires-Python: >=3.10,<4.0
Classifier: License :: OSI Approved :: MIT License
Classifier: Programming Language :: Python :: 3
Classifier: Programming Language :: Python :: 3.10
Classifier: Programming Language :: Python :: 3.11
Classifier: Programming Language :: Python :: 3.12
Project-URL: documentation, https://krunals-organization-2.gitbook.io/pydatavalidator
Project-URL: homepage, https://www.proalgotrader.com
Project-URL: repository, https://github.com/krunaldodiya/py-data-validator
